img_ai_prep/__init__.py
img_ai_prep/center_detection.py
img_ai_prep/crop.py
img_ai_prep/img_ai_prep.py
img_ai_prep/resize.py
img_ai_prep-0.0.1.dist-info/METADATA
img_ai_prep-0.0.1.dist-info/WHEEL
img_ai_prep-0.0.1.dist-info/top_level.txt
img_ai_prep-0.0.1.dist-info/RECORD
