Metadata-Version: 2.1
Name: img-ai-prep
Version: 0.0.1
Summary: Prepare images for AI model ingestion
Home-page: https://github.com/ikmckenz/img_ai_prep
Author: ikmckenz
Classifier: Programming Language :: Python :: 3
Requires-Dist: Pillow (>=9.3.0)
Requires-Dist: numpy (>=1.23.4)
Requires-Dist: opencv-python (>=4.6.0.66)
